complax/__init__.py
complax/complax.py
complax-1.0.1.dist-info/LICENSE
complax-1.0.1.dist-info/METADATA
complax-1.0.1.dist-info/WHEEL
complax-1.0.1.dist-info/entry_points.txt
complax-1.0.1.dist-info/top_level.txt
complax-1.0.1.dist-info/RECORD
