Metadata-Version: 2.1
Name: complax
Version: 1.0.1
Summary: A Python tool for automatic microsolvation and geometry optimization using xTB.
Home-page: https://github.com/Fedelau/complax
Author: Federica Lauria
Author-email: federica.lauria95@gmail.com
License: MIT
Keywords: compchem,microsolvation,xtb,geometry optimization
Classifier: Programming Language :: Python :: 3.11
Classifier: License :: OSI Approved :: MIT License
Classifier: Operating System :: OS Independent
Requires-Python: >=3.8
License-File: LICENSE
Requires-Dist: ase
Requires-Dist: colorama
Requires-Dist: numpy
Requires-Dist: tabulate
Requires-Dist: tqdm
